agents/__init__.py
agents/agents.py
agents/basic_agent.py
agents/influencer_agent.py
agents/manipulation_agent.py
agents/mcp_adapter.py
agents/navigation_agent.py
agents/perception_agent.py
agents/response.py
agents/tools.py
bandu_rai-0.1.2.dist-info/licenses/LICENSE
bandu_rai-0.1.2.dist-info/METADATA
bandu_rai-0.1.2.dist-info/WHEEL
bandu_rai-0.1.2.dist-info/top_level.txt
bandu_rai-0.1.2.dist-info/RECORD
