Metadata-Version: 2.4
Name: bandu-rai
Version: 0.1.2
Summary: Bandu: RAI Agent
Author-email: Sachin Kumar <sachinkumar.ar97@gmail.com>
License-Expression: MIT
Classifier: Programming Language :: Python :: 3
Classifier: Operating System :: OS Independent
Requires-Python: >=3.10
License-File: LICENSE
Requires-Dist: rai_core>=2.5.8
Requires-Dist: rai_whoami>=0.0.5
Requires-Dist: chainlit>=2.9.3
Requires-Dist: langchain>=0.3.27
Requires-Dist: langchain-mcp-adapters>=0.2.1
Requires-Dist: langchain-ollama>=0.3.10
Dynamic: license-file
